apeer_to_wipp_converter/__init__.py
apeer_to_wipp_converter/apeer_to_wipp_converter.py
apeer_to_wipp_converter/cli.py
apeer_to_wipp_converter-0.1.0.dist-info/AUTHORS.rst
apeer_to_wipp_converter-0.1.0.dist-info/LICENSE
apeer_to_wipp_converter-0.1.0.dist-info/METADATA
apeer_to_wipp_converter-0.1.0.dist-info/WHEEL
apeer_to_wipp_converter-0.1.0.dist-info/entry_points.txt
apeer_to_wipp_converter-0.1.0.dist-info/top_level.txt
apeer_to_wipp_converter-0.1.0.dist-info/RECORD
