Metadata-Version: 2.1
Name: apeer-to-wipp-converter
Version: 0.1.0
Summary: Convert APEER plugins to WIPP
Home-page: https://github.com/ktaletsk/apeer_to_wipp_converter
Author: Konstantin Taletskiy
Author-email: konstantin@taletskiy.com
License: MIT license
Keywords: apeer_to_wipp_converter
Platform: UNKNOWN
Classifier: Development Status :: 2 - Pre-Alpha
Classifier: Intended Audience :: Developers
Classifier: License :: OSI Approved :: MIT License
Classifier: Natural Language :: English
Classifier: Programming Language :: Python :: 3
Classifier: Programming Language :: Python :: 3.5
Classifier: Programming Language :: Python :: 3.6
Classifier: Programming Language :: Python :: 3.7
Classifier: Programming Language :: Python :: 3.8
Requires-Python: >=3.5
Requires-Dist: Click (>=7.0)
